pydxp/__init__.py
pydxp/__version__.py
pydxp/pydxp.py
pydxp-0.1.5.dist-info/LICENSE.txt
pydxp-0.1.5.dist-info/METADATA
pydxp-0.1.5.dist-info/WHEEL
pydxp-0.1.5.dist-info/top_level.txt
pydxp-0.1.5.dist-info/RECORD
