Metadata-Version: 2.1
Name: pydxp
Version: 0.1.5
Summary: Python module for Nectar DXP
Home-page: https://gitlab.com/wisetux/pydxp
Author: wisetux
Author-email: prasadkumar013@gmail.com
License: GPL
Platform: UNKNOWN
Classifier: Programming Language :: Python :: 3.7
Classifier: License :: OSI Approved :: GNU General Public License v3 or later (GPLv3+)
Classifier: Operating System :: OS Independent
Requires-Python: >=3.7.0
Requires-Dist: requests
